solarnet/__init__.py
solarnet/main.py
solarnet/data/__init__.py
solarnet/data/dataset_utils.py
solarnet/data/sdo_benchmark.py
solarnet/data/sdo_dataset.py
solarnet/data/transforms.py
solarnet/models/__init__.py
solarnet/models/backbone.py
solarnet/models/classifier.py
solarnet/models/crnn.py
solarnet/models/image_classification.py
solarnet/models/model_utils.py
solarnet/models/naive.py
solarnet/models/simclr.py
solarnet/models/simple_cnn.py
solarnet/models/squeezenet_module.py
solarnet/tasks/__init__.py
solarnet/tasks/dataset.py
solarnet/tasks/download_dataset.py
solarnet/tracking/__init__.py
solarnet/tracking/in_memory_logger.py
solarnet/utils/__init__.py
solarnet/utils/data.py
solarnet/utils/dict.py
solarnet/utils/filesystem.py
solarnet/utils/log.py
solarnet/utils/metrics.py
solarnet/utils/physics.py
solarnet/utils/plots.py
solarnet/utils/pytorch.py
solarnet/utils/s3.py
solarnet/utils/target.py
solarnet/utils/yaml.py
SolarNet_Lib-0.1.0.dist-info/LICENSE
SolarNet_Lib-0.1.0.dist-info/METADATA
SolarNet_Lib-0.1.0.dist-info/WHEEL
SolarNet_Lib-0.1.0.dist-info/entry_points.txt
SolarNet_Lib-0.1.0.dist-info/top_level.txt
SolarNet_Lib-0.1.0.dist-info/RECORD
