Metadata-Version: 2.1
Name: SolarNet-Lib
Version: 0.1.0
Summary: Deep Learning for Solar Physics Prediction
Home-page: https://gitlab.com/jdonzallaz/solarnet
Author: Jonathan Donzallaz
Author-email: jonathan.donzallaz@hefr.ch
License: MIT
Platform: UNKNOWN
Classifier: Programming Language :: Python :: 3
Classifier: License :: OSI Approved :: MIT License
Classifier: Operating System :: OS Independent
Requires-Python: >=3.6
Requires-Dist: boto3 (>=1.17.49)
Requires-Dist: colorlog (>=5.0.0)
Requires-Dist: click (<7.2.0,>=7.1.1)
Requires-Dist: lightning-bolts (>=0.3.4)
Requires-Dist: matplotlib (>=3.3.4)
Requires-Dist: numpy (>=1.17.2)
Requires-Dist: pandas (>=1.1.5)
Requires-Dist: Pillow (>=8.2.0)
Requires-Dist: pyarrow (>=4.0.0)
Requires-Dist: pytorch-lightning (>=1.3.8)
Requires-Dist: ruamel.yaml (>=0.16.1)
Requires-Dist: sunpy[net] (<3.0.0,>=2.0.0)
Requires-Dist: torch (>=1.6)
Requires-Dist: torchmetrics (>=0.4.1)
Requires-Dist: torchvision (>=0.7)
Requires-Dist: tqdm (>=4.41.0)
Requires-Dist: typer (>=0.3.2)
